visdcc/DataTable.py
visdcc/Network.py
visdcc/Run_js.py
visdcc/Visdcc.py
visdcc/__init__.py
visdcc/_imports_.py
visdcc/metadata.json
visdcc/package-info.json
visdcc/visdcc.min.js
visdcc/visdcc.min.js.map
visdcc-0.0.63.dist-info/LICENSE
visdcc-0.0.63.dist-info/METADATA
visdcc-0.0.63.dist-info/WHEEL
visdcc-0.0.63.dist-info/top_level.txt
visdcc-0.0.63.dist-info/RECORD
