Metadata-Version: 2.2
Name: visdcc
Version: 0.0.63
Summary: Dash Components for Visualization.
Author: jimmybow <jimmybow@hotmail.com.tw>
License: MIT
Classifier: Framework :: Dash
Classifier: License :: OSI Approved :: MIT License
Classifier: Programming Language :: Python
License-File: LICENSE
Requires-Dist: dash>=3.0.0
Dynamic: author
Dynamic: classifier
Dynamic: description
Dynamic: description-content-type
Dynamic: license
Dynamic: requires-dist
Dynamic: summary
